{"nodes":[{"id":"core_config","label":"config.py","file_type":"code","source_file":"backend/app/core/config.py","source_location":"L1"},{"id":"core_config_settings","label":"Settings","file_type":"code","source_file":"backend/app/core/config.py","source_location":"L5"},{"id":"basesettings","label":"BaseSettings","file_type":"code","source_file":"","source_location":""},{"id":"core_config_settings_validate_db_url","label":".validate_db_url()","file_type":"code","source_file":"backend/app/core/config.py","source_location":"L78"}],"edges":[{"source":"core_config","target":"pydantic","relation":"imports_from","confidence":"EXTRACTED","source_file":"backend/app/core/config.py","source_location":"L1","weight":1},{"source":"core_config","target":"pydantic_settings","relation":"imports_from","confidence":"EXTRACTED","source_file":"backend/app/core/config.py","source_location":"L2","weight":1},{"source":"core_config","target":"core_config_settings","relation":"contains","confidence":"EXTRACTED","source_file":"backend/app/core/config.py","source_location":"L5","weight":1},{"source":"core_config_settings","target":"basesettings","relation":"inherits","confidence":"EXTRACTED","source_file":"backend/app/core/config.py","source_location":"L5","weight":1},{"source":"core_config_settings","target":"core_config_settings_validate_db_url","relation":"method","confidence":"EXTRACTED","source_file":"backend/app/core/config.py","source_location":"L78","weight":1}]}